odoo/addons/ssi_account_move_py3o_report/README.rst
odoo/addons/ssi_account_move_py3o_report/__init__.py
odoo/addons/ssi_account_move_py3o_report/__manifest__.py
odoo/addons/ssi_account_move_py3o_report/reports/account_move.odt
odoo/addons/ssi_account_move_py3o_report/reports/account_move_report.xml
odoo/addons/ssi_account_move_py3o_report/static/description/icon.png
odoo14_addon_ssi_account_move_py3o_report-14.0.1.1.2.dev1.dist-info/METADATA
odoo14_addon_ssi_account_move_py3o_report-14.0.1.1.2.dev1.dist-info/WHEEL
odoo14_addon_ssi_account_move_py3o_report-14.0.1.1.2.dev1.dist-info/top_level.txt
odoo14_addon_ssi_account_move_py3o_report-14.0.1.1.2.dev1.dist-info/RECORD
